jupylot/__init__.py
jupylot/_version.py
jupylot-0.1.1.data/data/share/jupyter/labextensions/jupylot/package.json
jupylot-0.1.1.data/data/share/jupyter/labextensions/jupylot/static/568.2fc7cc4ef210ff0ef700.js
jupylot-0.1.1.data/data/share/jupyter/labextensions/jupylot/static/747.b43b2818154c113b0160.js
jupylot-0.1.1.data/data/share/jupyter/labextensions/jupylot/static/865.0de80abf43a3862195b8.js
jupylot-0.1.1.data/data/share/jupyter/labextensions/jupylot/static/remoteEntry.02b4878c8e7dd1f6c74f.js
jupylot-0.1.1.data/data/share/jupyter/labextensions/jupylot/static/style.js
jupylot-0.1.1.data/data/share/jupyter/labextensions/jupylot/static/third-party-licenses.json
jupylot-0.1.1.data/data/share/jupyter/labextensions/jupylot/install.json
jupylot-0.1.1.dist-info/METADATA
jupylot-0.1.1.dist-info/WHEEL
jupylot-0.1.1.dist-info/licenses/LICENSE
jupylot-0.1.1.dist-info/RECORD
