Metadata-Version: 2.1
Name: jupylot
Version: 0.1.1
Summary: Error checking assistant for JupyterLab
Project-URL: Homepage, https://github.com/vrvrv/jupylot.git
Project-URL: Bug Tracker, https://github.com/vrvrv/jupylot.git/issues
Project-URL: Repository, https://github.com/vrvrv/jupylot.git.git
Author-email: "jinhwan.suk" <jinhwan.suk@linecorp.com>
License: BSD 3-Clause License
License-File: LICENSE
Classifier: Framework :: Jupyter
Classifier: Framework :: Jupyter :: JupyterLab
Classifier: Framework :: Jupyter :: JupyterLab :: 4
Classifier: Framework :: Jupyter :: JupyterLab :: Extensions
Classifier: Framework :: Jupyter :: JupyterLab :: Extensions :: Prebuilt
Classifier: License :: OSI Approved :: BSD License
Classifier: Programming Language :: Python
Classifier: Programming Language :: Python :: 3
Classifier: Programming Language :: Python :: 3.8
Classifier: Programming Language :: Python :: 3.9
Classifier: Programming Language :: Python :: 3.10
Classifier: Programming Language :: Python :: 3.11
Requires-Python: >=3.8
